dash_google_auth_email
