Metadata-Version: 1.1
Name: dash-google-auth-email
Version: 1.9.99
Summary: Dash Google Auth Email
Home-page: https://github.com/ricklentz/dash-google-auth-email
Author: Rick Lentz
Author-email: rlentz@amfam.com
License: MIT
Platform: UNKNOWN
Classifier: License :: OSI Approved :: MIT License
Classifier: Programming Language :: Python
Classifier: Programming Language :: Python :: Implementation :: CPython
